{
  "version": "G40.1",
  "phase": "2A",
  "scope": "simulation-modulehost-adapter",
  "filesCreated": [
    "js/modules/egt-simulation-engine.js",
    "css/egt-simulation.css",
    "docs/G40_1_PHASE2_SIMULATION_MODULEHOST_REPORT.md",
    "docs/G40_1_PHASE2_SIMULATION_MODULEHOST_QA.json"
  ],
  "filesChanged": [
    "index.html",
    "js/app.js",
    "js/core/app-config.js",
    "service-worker.js",
    "update-check.json",
    "manifest.json",
    "module-manifest.json",
    "docs/WORKING-PLAN.md",
    "../WORKING-PLAN_1.md"
  ],
  "checks": {
    "nodeCheckAllJs": true,
    "jsonManifestValid": true,
    "jsonUpdateCheckValid": true,
    "jsonModuleManifestValid": true,
    "serviceWorkerAssetsExist": true,
    "htmlReferencesExist": true,
    "playwrightAvailable": false,
    "browserRuntimeTested": false,
    "chromiumBinaryAvailable": true,
    "chromiumHeadlessDomDumpCompleted": false,
    "chromiumHeadlessNote": "chromium vorhanden, file:// DOM dump lief in dieser Umgebung in Timeout; nicht als bestandener Runtime-Test gewertet"
  },
  "knownOpenWork": [
    "Move showQuestion/tickTimer/renderAnswers/updateQuestionNav from app.js into egt-simulation-engine.js",
    "Move answer recording/navigation/result rendering from app.js into egt-simulation-engine.js",
    "Keep buildQuiz/generators as QuestionPool until later extraction",
    "Run real browser smoke test after Playwright/Puppeteer is available"
  ],
  "status": "Phase 2A complete; Phase 2B next"
}