{
  "version": "G45.0",
  "phase": "Phase 7",
  "title": "GeneratorRegistry / Pool-Grenze",
  "createdAt": "2026-06-15",
  "staticQa": {
    "jsSyntaxCheck": "passed: 63 files",
    "jsonValidation": "passed: 64 files",
    "serviceWorkerAssetCheck": "passed: 193 assets, 0 missing",
    "zipTest": "pending-run",
    "browserLiveTest": "not-run"
  },
  "createdFiles": [
    "js/core/generator-registry.js",
    "docs/G45_0_PHASE7_GENERATOR_REGISTRY_REPORT.md",
    "docs/G45_0_PHASE7_GENERATOR_REGISTRY_QA.json"
  ],
  "changedFiles": [
    "js/app.js",
    "index.html",
    "js/core/architecture-guard.js",
    "js/core/module-host.js",
    "js/core/branch-question-pools.js",
    "service-worker.js",
    "js/core/app-config.js",
    "update-check.json",
    "manifest.json",
    "module-manifest.json",
    "WORKING-PLAN_1.md",
    "docs/WORKING-PLAN.md"
  ],
  "notChanged": [
    "Firebase config",
    "Admin/Auth/Profile session keys",
    "Highscore schema",
    "Coach memory",
    "Demo limits",
    "CTC-Lohr block structure",
    "Result/Review logic"
  ],
  "nextRecommendedPhase": "Phase 8: QuestionBank-/Datenpool-Grenze pro Branch oder BuildQuiz-Orchestrator weiter aus app.js lösen",
  "notes": [
    "Static code validation completed in container.",
    "Browser live test was not run.",
    "Generator functions remain in app.js; only pool blueprint/resolver boundary was extracted."
  ]
}